PayPaython
