Metadata-Version: 2.1
Name: PayPaython
Version: 2.5.1
Summary: An API wrapper for the PayPayAPI
Home-page: https://github.com/taka-4602/PayPaython
Author: taka4602
Author-email: shun4602@gmail.com
Keywords: paypay
Classifier: Programming Language :: Python :: 3
Classifier: License :: OSI Approved :: MIT License
Classifier: Operating System :: OS Independent
Requires-Python: >=3.6
